<?xml version="1.0"?>
<!-- Манифест для циферблата Garmin Descent MK3i -->
<iq:manifest xmlns:iq="http://www.garmin.com/xml/connectiq" version="3">
    <iq:application
        entry="DescentWatchfaceApp"
        id="a1b2c3d4-e5f6-7890-abcd-123456789def"
        launcherIcon="@Drawables.LauncherIcon"
        minSdkVersion="3.0.0"
        name="@Strings.AppName"
        type="watchface"
        version="1.0.0">

        <iq:products>
            <!-- Descent MK3i 43mm -->
            <iq:product id="descentmk343mm"/>
        </iq:products>

        <iq:permissions/>

        <iq:languages>
            <!-- Поддерживаемые языки -->
            <iq:language>eng</iq:language>
            <iq:language>rus</iq:language>
        </iq:languages>

        <iq:barrels/>

    </iq:application>
</iq:manifest>
